morphy/__init__.py
morphy/errors.py
morphy/interfaces.py
morphy/lang.py
morphy/settings.py
morphy/preprocessing/__init__.py
morphy/preprocessing/multilang.py
morphy/preprocessing/russian.py
morphy/preprocessing/types.py
morphy-0.1.dist-info/LICENSE
morphy-0.1.dist-info/METADATA
morphy-0.1.dist-info/WHEEL
morphy-0.1.dist-info/top_level.txt
morphy-0.1.dist-info/RECORD
