Metadata-Version: 2.1
Name: morphy
Version: 0.1
Summary: Smart tool for morphological analysis
Home-page: https://bitbucket.org/igor_ezersky/morphy
Author: Igor Ezersky
Author-email: igor.ezersky.work@gmail.com
License: UNKNOWN
Platform: UNKNOWN
Classifier: Programming Language :: Python :: 3
Classifier: License :: OSI Approved :: MIT License
Classifier: Operating System :: OS Independent
